midi_trans/__init__.py
midi_trans/melodyandremidi.py
midi_trans-0.1.1.dist-info/LICENSE
midi_trans-0.1.1.dist-info/METADATA
midi_trans-0.1.1.dist-info/WHEEL
midi_trans-0.1.1.dist-info/top_level.txt
midi_trans-0.1.1.dist-info/RECORD
