Metadata-Version: 2.2
Name: midi-trans
Version: 0.1.1
Summary: A tool for MIDI melody extraction and rearrangement
Home-page: https://github.com/yourusername/midi-trans
Author: Your Name
Author-email: your.email@example.com
Classifier: Programming Language :: Python :: 3
Classifier: License :: OSI Approved :: MIT License
Classifier: Operating System :: OS Independent
Requires-Python: >=3.6
License-File: LICENSE
Requires-Dist: mido
Requires-Dist: musicpy
Dynamic: author
Dynamic: author-email
Dynamic: classifier
Dynamic: description
Dynamic: description-content-type
Dynamic: home-page
Dynamic: requires-dist
Dynamic: requires-python
Dynamic: summary
